{
  "zh_news": {
    "頭條新聞": [
      {
        "title": "美學者：擒馬杜洛展罕見協同能力 中國無法對台複製",
        "link": "https://www.cna.com.tw/news/aipl/202601070013.aspx",
        "source": "中央社",
        "published": "2026-01-06T14:39:00+00:00",
        "summary": "美國總統川普日前發動突襲，成功擒獲委內瑞拉總統馬杜洛，整個行動持續約140分鐘。華府資深國防學者坎西恩指出，此次行動展現了美軍「全球非常罕見的協同作戰能力」，這一能力是經過數十年的努力所達成，並且在此..."
      },
      {
        "title": "F-16V失聯飛官疑跳傘 海巡署調派3艦6艇搜救",
        "link": "https://www.cna.com.tw/news/aipl/202601060359.aspx",
        "source": "中央社",
        "published": "2026-01-06T07:34:24+00:00",
        "summary": "F-16V飛官辛姓於6日晚間疑似在花蓮豐濱外海跳傘，空軍隨即展開救援行動。海巡署獲報後，迅速成立應變中心，指揮調度3艘艦艇及6艘救援艇前往現場進行搜救。由於當地海象惡劣，伴隨低溫及巨浪，海巡署同時聯繫..."
      },
      {
        "title": "F-16V飛官花蓮外海疑跳傘 入夜海象惡劣持續搜救",
        "link": "https://www.cna.com.tw/news/aipl/202601060353.aspx",
        "source": "中央社",
        "published": "2026-01-06T06:50:08+00:00",
        "summary": "空軍辛姓上尉駕駛F-16V單座戰機，於6日晚間在花蓮縣豐濱鄉東面約10浬處疑似跳傘。事件發生後，海巡署立即動員3艘艦艇及6艘小艇，並與國防部等相關單位展開全力搜救行動。隨著夜幕降臨，海象惡劣，搜救工作..."
      },
      {
        "title": "空軍：F-16V夜訓失聯 飛官飛行總時數611小時",
        "link": "https://www.cna.com.tw/news/aipl/202601060347.aspx",
        "source": "中央社",
        "published": "2026-01-06T06:10:55+00:00",
        "summary": "空軍一架F-16V戰機於今日晚間在花蓮豐濱鄉東面10浬處失聯，飛官辛柏毅上尉疑似已跳傘，目前各單位正展開搜救行動。據空軍資料，辛柏毅執行夜間飛行訓練，飛行總時數為611小時，其中F-16V機種的飛行時..."
      },
      {
        "title": "卓榮泰：台日關係更友好 印太地區更安全",
        "link": "https://www.cna.com.tw/news/aipl/202601060338.aspx",
        "source": "中央社",
        "published": "2026-01-06T05:45:33+00:00",
        "summary": "行政院長卓榮泰與新任台灣日本關係協會會長謝長廷於6日共同出席「吃海鮮．挺日本」活動。卓榮泰指出，總統賴清德特別請謝長廷推進台日關係，強調台日關係的友好程度將有助於提升印太地區的安全。謝長廷則表達期望，..."
      },
      {
        "title": "F-16V飛官疑跳傘 搜救機抵達目標區、周邊貨輪助搜救",
        "link": "https://www.cna.com.tw/news/aipl/202601060333.aspx",
        "source": "中央社",
        "published": "2026-01-06T05:08:20+00:00",
        "summary": "一架由辛姓上尉駕駛的F-16V（blk20）單座戰機（機號6700）於6日晚間執行例行性訓練任務時，於7時29分在花蓮縣豐濱鄉東面10浬處疑似發生跳傘事件。海巡署隨即出動北部、東部及南部海域的艦艇進行..."
      },
      {
        "title": "林佳龍午宴歐洲議會議員團 盼共同守護關鍵基礎設施",
        "link": "https://www.cna.com.tw/news/aipl/202601060332.aspx",
        "source": "中央社",
        "published": "2026-01-06T05:04:18+00:00",
        "summary": "外交部長林佳龍於6日午宴接待歐洲議會議員訪團，並在社群媒體上分享此次會議內容。他強調台灣在通訊及供應鏈安全方面的努力，並期望與歐洲夥伴共同守護關鍵基礎設施。林佳龍指出，台灣與歐洲的產業具有高度互補性，..."
      },
      {
        "title": "F-16V飛官疑跳傘 卓榮泰指示海巡空勤協助搜救",
        "link": "https://www.cna.com.tw/news/aipl/202601060331.aspx",
        "source": "中央社",
        "published": "2026-01-06T05:04:16+00:00",
        "summary": "空軍於6日發布消息，駕駛F-16V（blk20）單座戰機的辛姓上尉疑似在花蓮外海跳傘，隨即展開搜救行動。行政院長卓榮泰當晚聯繫國防部長顧立雄以了解事件進展，並指示海巡署、空勤總隊及農業部等相關單位協助..."
      }
    ],
    "產經": [
      {
        "title": "Vera Rubin全面量產 黃仁勳：與台積電合作規模龐大",
        "link": "https://www.cna.com.tw/news/ait/202601070015.aspx",
        "source": "中央社",
        "published": "2026-01-06T15:31:08+00:00",
        "summary": "輝達在CES大會上宣布其新一代AI超級電腦Vera Rubin已全面量產，該系統由六款全新晶片組成。輝達執行長黃仁勳在國際記者會中指出，預期今年與台積電的合作將達到相當龐大的規模，並透露輝達與台積電相..."
      },
      {
        "title": "CES展登場 宏碁、華碩多家台廠推AI新品",
        "link": "https://www.cna.com.tw/news/ait/202601060282.aspx",
        "source": "中央社",
        "published": "2026-01-06T02:25:30+00:00",
        "summary": "消費性電子展（CES）於美國時間6日至9日在拉斯維加斯舉行，吸引多家台灣廠商參展，包括宏碁、華碩、技嘉及微星等。這些公司在展會上推出了多款人工智慧（AI）相關新產品，涵蓋範疇包括筆記型電腦、商務筆電、..."
      },
      {
        "title": "新疆油田年注碳破百萬噸 CCUS商用化重要里程碑",
        "link": "https://www.cna.com.tw/news/ait/202601060224.aspx",
        "source": "中央社",
        "published": "2026-01-06T00:58:26+00:00",
        "summary": "中國石油天然氣集團（CNPC）旗下的一處旗艦油田在2023年內成功注入超過100萬公噸二氧化碳，這一成就被北京視為碳捕捉、利用與封存（CCUS）技術商用化的重要里程碑。該技術的推廣被認為對於減少溫室氣..."
      },
      {
        "title": "超微AI領域迎戰輝達 蘇姿丰秀台積電2奈米AI加速器",
        "link": "https://www.cna.com.tw/news/ait/202601060212.aspx",
        "source": "中央社",
        "published": "2026-01-06T00:31:00+00:00",
        "summary": "超微（AMD）執行長蘇姿丰於1月5日在拉斯維加斯舉行的CES展會上發表主題演講，重點聚焦於人工智慧（AI）領域的發展。她展示了AI伺服器機櫃及與合作夥伴共同開發的人形機器人，強調超微在AI市場中與輝達..."
      }
    ],
    "全球國際新聞": [
      {
        "title": "白宮：取得格陵蘭為美國安優先事項 不排除動用軍隊",
        "link": "https://www.cna.com.tw/news/aopl/202601070014.aspx",
        "source": "中央社",
        "published": "2026-01-06T15:18:05+00:00",
        "summary": "美國白宮表示，取得格陵蘭已成為美國國家安全的優先事項，並強調這對於在北極地區威懾美國對手至關重要。總統川普及其政府團隊正在討論多種選項以推動此目標，其中包括動用美軍的可能性。此言論再次突顯美國對格陵蘭..."
      },
      {
        "title": "路透：委內瑞拉正與美國官員洽談石油出口",
        "link": "https://www.cna.com.tw/news/aopl/202601070012.aspx",
        "source": "中央社",
        "published": "2026-01-06T14:27:58+00:00",
        "summary": "委內瑞拉目前正與美國官員進行洽談，討論將石油出口至美國煉油廠的相關事宜。根據路透社報導，消息來源包括五名政府、業界及航運業人士。這一舉措可能標誌著兩國在能源領域的關係有所改善，並可能對全球石油市場產生..."
      },
      {
        "title": "談11月期中選舉 川普：共和黨必須贏否則我會被彈劾",
        "link": "https://www.cna.com.tw/news/aopl/202601070009.aspx",
        "source": "中央社",
        "published": "2026-01-06T13:10:50+00:00",
        "summary": "美國總統川普於11月期中選舉前，向共和黨國會議員強調必須贏得選舉，否則將面臨民主黨的彈劾威脅。他指出，若共和黨失利，民主黨將尋找理由對他進行彈劾。川普在其第一任期內曾兩度遭到民主黨主導的眾議院彈劾，理..."
      },
      {
        "title": "35國出席巴黎峰會挺烏克蘭安全 義大利：不會派兵",
        "link": "https://www.cna.com.tw/news/aopl/202601070008.aspx",
        "source": "中央社",
        "published": "2026-01-06T13:07:48+00:00",
        "summary": "支持烏克蘭的「志願者聯盟」峰會於6日在法國巴黎舉行，吸引35個國家參加。義大利總理梅洛尼重申，義大利不會向烏克蘭派遣軍隊。與此同時，德國表示可能會在烏克蘭附近的北約國家部署軍隊，以增強該地區的安全防衛..."
      },
      {
        "title": "伊朗經濟抗議潮加劇 警民衝突已釀逾27死",
        "link": "https://www.cna.com.tw/news/aopl/202601070007.aspx",
        "source": "中央社",
        "published": "2026-01-06T12:29:45+00:00",
        "summary": "伊朗因經濟困境引發的抗議活動已持續10天，並持續加劇。根據法斯通訊社報導，抗議活動中一名警察在伊朗西部遭槍殺，警民衝突至今已造成至少27名抗議者喪生。抗議活動主要集中在經濟問題上，民眾對於生活困難和政..."
      },
      {
        "title": "美軍逮捕馬杜洛 古巴與委內瑞拉估造成55軍人殉職",
        "link": "https://www.cna.com.tw/news/aopl/202601070006.aspx",
        "source": "中央社",
        "published": "2026-01-06T12:22:43+00:00",
        "summary": "美軍近日在委內瑞拉進行突襲，逮捕該國領袖馬杜洛。根據古巴和委內瑞拉政府公布的資料，此次行動導致兩國合計55名軍人殉職。事件發生後，兩國政府對此表示強烈譴責，並指責美方的行動對地區穩定造成威脅。此事件引..."
      },
      {
        "title": "瑞士酒吧大火案業者致歉 慘重傷亡引發超收質疑",
        "link": "https://www.cna.com.tw/news/aopl/202601070005.aspx",
        "source": "中央社",
        "published": "2026-01-06T11:04:40+00:00",
        "summary": "瑞士一間酒吧在跨年夜發生大火，造成40人喪生，至少116人受傷。酒吧業者對此事件表示「悲痛欲絕」，並承諾全力配合調查。此次火災引發了對酒吧是否超過容納限制的質疑，因為死傷人數慘重。當地警方和消防部門已..."
      },
      {
        "title": "聯準會理事米蘭：2026年有必要降息逾1個百分點",
        "link": "https://www.cna.com.tw/news/aopl/202601070004.aspx",
        "source": "中央社",
        "published": "2026-01-06T10:43:37+00:00",
        "summary": "美國聯邦準備理事會理事米蘭在接受媒體專訪時表示，聯準會的政策目前顯示出限制性，對經濟發展造成抑制。他指出，預計在2026年有必要將基準利率大幅調降逾1個百分點，以促進經濟增長。米蘭的發言反映出對當前貨..."
      }
    ],
    "社會": [
      {
        "title": "桃園男大生課堂昏迷送醫不治 初判心因性猝死",
        "link": "https://www.cna.com.tw/news/asoc/202601060356.aspx",
        "source": "中央社",
        "published": "2026-01-06T06:54:15+00:00",
        "summary": "桃園市某大學一名男大生於6日上課時昏迷，經現場急救後送醫，但最終不治。法醫初步判定其死因為心因性猝死，是否與近期全台低溫氣候有關尚待進一步調查。校方對此事件表示無法回應。"
      },
      {
        "title": "劉世芳赴新北拜訪 侯友宜：配合中央攜手推社宅",
        "link": "https://www.cna.com.tw/news/aloc/202601060316.aspx",
        "source": "中央社",
        "published": "2026-01-06T04:15:44+00:00",
        "summary": "內政部長劉世芳於6日拜訪新北市市長侯友宜，雙方針對社會住宅及相關住宅政策進行了意見交流。侯友宜表示，新北市將配合中央的社會住宅政策，並強調將攜手合作，持續推動社會住宅的興辦。此次會議旨在促進地方與中央..."
      },
      {
        "title": "測速照相執法爭議 警署：工程改善先行為原則",
        "link": "https://www.cna.com.tw/news/asoc/202601060298.aspx",
        "source": "中央社",
        "published": "2026-01-06T03:06:05+00:00",
        "summary": "近來國內區間測速照相的密度引發了廣泛的爭議。針對此問題，內政部警政署於6日表示，將以「工程改善先行」為原則進行測速照相執法。警政署計劃儘速邀集交通部及專家學者，針對「取締一般交通違規作業程序」進行研修..."
      },
      {
        "title": "北捷獲贈50支新型防暴鋼叉 強化維安應變量能",
        "link": "https://www.cna.com.tw/news/aloc/202601060296.aspx",
        "source": "中央社",
        "published": "2026-01-06T02:53:00+00:00",
        "summary": "台北捷運公司於6日宣布，獲得北市府市政顧問陳啟宏捐贈的50支新型防暴鋼叉，此舉旨在加強捷運系統的維安應變能力。此次捐贈是在去年底發生的無差別傷害事件後進行的，北市捷運警察隊隊長廖洛育及北捷總經理黃清信..."
      },
      {
        "title": "淡水古蹟博物館充氣馬亮相 音樂市集週末登場",
        "link": "https://www.cna.com.tw/news/aloc/202601060286.aspx",
        "source": "中央社",
        "published": "2026-01-06T02:39:39+00:00",
        "summary": "淡水古蹟博物館於農曆馬年之際，邀請藝術家創作三隻大型充氣馬，並於紅毛城展出。這項展覽旨在吸引民眾前來參觀，體驗藝術與歷史的結合。此外，博物館將於本週末舉辦音樂市集，集合來自台灣及日本的品牌，為參加者提..."
      },
      {
        "title": "北市國中小午餐全免費 教育局估預算約20億",
        "link": "https://www.cna.com.tw/news/aloc/202601060280.aspx",
        "source": "中央社",
        "published": "2026-01-06T02:20:26+00:00",
        "summary": "台北市長蔣萬安宣布將於今年實施國中小營養午餐全面免費政策。對此，部分議員對政策推動過程表示質疑，認為過程草率。台北市教育局長湯志民在議會委員會中表示，該政策的初步預算估計約需20億元，將透過追加減方式..."
      },
      {
        "title": "民進黨建議提名34席 拚2026高雄市議員選舉過半",
        "link": "https://www.cna.com.tw/news/aloc/202601060277.aspx",
        "source": "中央社",
        "published": "2026-01-06T02:18:20+00:00",
        "summary": "民進黨高雄市黨部於6日通過鳳山區及前鎮、小港區市議員提名席次規劃，並將此前通過的提名計畫整合，確定2026年市議員選舉的提名席次。根據規劃，民進黨將提名34席，這不包括原住民席次。該黨的目標是力爭在市..."
      },
      {
        "title": "屏縣攜手慈善團體 春節前夕送暖7545戶現金物資",
        "link": "https://www.cna.com.tw/news/aloc/202601060275.aspx",
        "source": "中央社",
        "published": "2026-01-06T02:16:16+00:00",
        "summary": "屏東縣政府與民間慈善團體合作，計劃在春節前夕向全縣7545戶低收入家庭發放現金及物資。每戶將獲得1000元現金，並提供米、醬油或棉被等生活必需品。此外，屏東縣政府自今年1月起開放社會福利補助的線上申請..."
      }
    ],
    "生活": [
      {
        "title": "乾冷空氣南下入夜極寒冷 吳德榮：8至10日輻射冷卻強探5度以下",
        "link": "https://www.cna.com.tw/news/ahel/202601070021.aspx",
        "source": "中央社",
        "published": "2026-01-06T16:31:21+00:00",
        "summary": "氣象署發布低溫特報，預測8日至10日將受到強烈大陸冷氣團及輻射冷卻影響，部分地區氣溫將探至攝氏5度以下。今天清晨至晚間，西半部、宜蘭及金門等17個縣市需注意低於10度的低溫情況。本島平地今日清晨最低溫..."
      },
      {
        "title": "自動售票機故障第3天 台鐵致歉：儘速排除異常",
        "link": "https://www.cna.com.tw/news/ahel/202601060349.aspx",
        "source": "中央社",
        "published": "2026-01-06T06:27:59+00:00",
        "summary": "台鐵自動售票機於4日發生故障，至今已持續第3天。台鐵產工表示，事發後已啟動應變機制，並持續全面檢視設備及系統設定，力求儘速排除異常。台鐵對於此次事件造成旅客的不便表示歉意。"
      },
      {
        "title": "今彩539第115005期 頭獎4注中獎",
        "link": "https://www.cna.com.tw/news/ahel/202601060345.aspx",
        "source": "中央社",
        "published": "2026-01-06T06:07:51+00:00",
        "summary": "今彩539第115005期於6日開獎，開獎號碼為02、01、11、33、06。此次派彩結果顯示，頭獎共中獎4注，每注獎金為新台幣600萬元。"
      },
      {
        "title": "大樂透第115002期頭獎槓龜",
        "link": "https://www.cna.com.tw/news/ahel/202601060343.aspx",
        "source": "中央社",
        "published": "2026-01-06T06:04:46+00:00",
        "summary": "大樂透第115002期於今晚開獎，開獎號碼為33、45、23、02、39、38，特別號為06。根據派彩結果，本期頭獎未有人中獎，顯示出頭獎槓龜的情況。此次開獎吸引了眾多彩迷的關注，但最終未能產生頭獎得..."
      },
      {
        "title": "大樂透第115002期開獎",
        "link": "https://www.cna.com.tw/news/ahel/202601060327.aspx",
        "source": "中央社",
        "published": "2026-01-06T04:53:07+00:00",
        "summary": "大樂透第115002期於今晚開獎，開獎號碼為33、45、23、02、39、38，特別號為06。此次開獎吸引了眾多彩民的關注，具體中獎情況及獎金分配尚待後續公布。"
      },
      {
        "title": "今彩539第115005期開獎",
        "link": "https://www.cna.com.tw/news/ahel/202601060323.aspx",
        "source": "中央社",
        "published": "2026-01-06T04:44:59+00:00",
        "summary": "今彩539第115005期於6日開獎，中獎號碼為02、01、11、33、06。此次開獎中，3星彩中獎號碼為783，4星彩中獎號碼為0122。此次開獎結果吸引了眾多彩迷的關注，相關獎金及中獎者的具體情況..."
      },
      {
        "title": "復健導入互動AI遊戲 中風翁重拾吞嚥進食能力",
        "link": "https://www.cna.com.tw/news/ahel/202601060302.aspx",
        "source": "中央社",
        "published": "2026-01-06T03:17:13+00:00",
        "summary": "恭紀念醫院與中原大學生物醫學工程研究所合作，開發了一款以吞嚥運動為核心的互動式AI遊戲，旨在提升中風患者的吞嚥復健成效。該遊戲專注於強化口咽肌群功能，並成功幫助一名中風老翁移除鼻胃管，恢復正常進食。此..."
      },
      {
        "title": "台灣藝術家廖繼春逝世50週年 國美館2月推個展",
        "link": "https://www.cna.com.tw/news/acul/202601060300.aspx",
        "source": "中央社",
        "published": "2026-01-06T03:13:09+00:00",
        "summary": "台灣藝術家廖繼春於今年逝世50週年，國立台灣美術館預計在2月舉辦其個展，展出廖繼春的藝術作品。廖繼春曾與顏水龍、陳澄波等知名藝術家共同創立台陽美術協會，對台灣藝術界有重要貢獻。此外，國美館在3月將推出..."
      }
    ],
    "娛樂": [
      {
        "title": "林志穎睽違16年重返「紅白」 稱像新人第一次演出",
        "link": "https://www.cna.com.tw/news/amov/202601060348.aspx",
        "source": "中央社",
        "published": "2026-01-06T06:13:57+00:00",
        "summary": "台視將於2026年舉辦「超級巨星紅白藝能大賞」，公開卡司包括日本男團King&Prince、林志穎、蘇慧倫及告五人等。林志穎在此活動中重返舞台，距離他上次參加已經過去16年。他表示對這個舞台感到既熟悉..."
      },
      {
        "title": "王淨「功夫」唯一女力 高強度武打訓練不退縮",
        "link": "https://www.cna.com.tw/news/amov/202601060339.aspx",
        "source": "中央社",
        "published": "2026-01-06T05:47:36+00:00",
        "summary": "演員王淨在導演九把刀執導的電影《功夫》中擔任唯一女性角色，面對高強度的武打訓練表現出色。她的努力獲得同劇演員戴立忍的讚賞，稱讚她成功地支撐起片中充滿想像力的奇幻動作世界觀。王淨的表現不僅展示了她的專業..."
      },
      {
        "title": "葉啟田否認罹失智症 仍想參政嘆選舉太花錢",
        "link": "https://www.cna.com.tw/news/amov/202601060307.aspx",
        "source": "中央社",
        "published": "2026-01-06T03:33:24+00:00",
        "summary": "寶島歌王葉啟田近日將擔任「真愛秀．藍寶石大歌廳」演唱會的嘉賓，這是他多年來首次公開演唱。對於外界傳聞他罹患失智症，葉啟田予以否認，並表示仍有意參政，但對於選舉的高昂花費表示擔憂。他提到目前的心願是能夠..."
      },
      {
        "title": "動物方城市2打破紀錄 成為中國票房最高好萊塢電影",
        "link": "https://www.cna.com.tw/news/amov/202601060211.aspx",
        "source": "中央社",
        "published": "2026-01-06T00:28:58+00:00",
        "summary": "「動物方城市2」截至5日已在中國創下票房42.51億元人民幣（約191億元新台幣），成為中國影史上票房最高的好萊塢電影，打破了先前由「復仇者聯盟：終局之戰」保持的紀錄。該片的成功顯示了其在中國市場的廣..."
      }
    ],
    "運動": [
      {
        "title": "CTPBA職撞年度總冠軍戰 柯秉逸逆轉勝菲國小將稱王",
        "link": "https://www.cna.com.tw/news/aspt/202601060354.aspx",
        "source": "中央社",
        "published": "2026-01-06T06:50:10+00:00",
        "summary": "在CTPBA職業撞球巡迴賽總冠軍戰中，台灣選手柯秉逸於6日進行的決賽中，面對菲律賓選手馬納斯，曾一度落後4局。最終，柯秉逸在搶尾局以13比12逆轉獲勝，成功奪冠。此役展現了柯秉逸的堅韌與技術，並讓他在..."
      },
      {
        "title": "PLG領航猿6人得分雙位數 輕取勇士開季6連勝",
        "link": "https://www.cna.com.tw/news/aspt/202601060341.aspx",
        "source": "中央社",
        "published": "2026-01-06T05:57:40+00:00",
        "summary": "台灣職籃PLG桃園璞園領航猿於6日作客台北富邦勇士，最終以118比97獲勝，成功取得開季第六連勝。比賽中，領航猿全隊共有六名球員得分達雙位數，並且團隊共送出34次助攻，展現出良好的團隊合作。此役後，領..."
      },
      {
        "title": "義大利冬奧開幕倒數1個月 國際奧會：有信心如期就緒",
        "link": "https://www.cna.com.tw/news/aspt/202601060336.aspx",
        "source": "中央社",
        "published": "2026-01-06T05:31:27+00:00",
        "summary": "距離義大利米蘭-柯蒂納冬季奧運開幕僅剩1個月，部分場館的工程延誤引發外界關注。國際奧林匹克委員會執行長杜比於6日接受法新社訪問時表示，儘管存在這些挑戰，他對於所有準備工作能如期完成仍然充滿信心。義大利..."
      },
      {
        "title": "周天成不言老 BWF馬來西亞公開賽首輪宰林俊易",
        "link": "https://www.cna.com.tw/news/aspt/202601060278.aspx",
        "source": "中央社",
        "published": "2026-01-06T02:18:22+00:00",
        "summary": "台灣羽球選手周天成在BWF馬來西亞公開賽首輪中，以21比14、21比12擊敗同胞林俊易，成功晉級16強。比賽於6日進行，周天成在僅40分鐘內完成比賽，展現出穩定的表現。周天成即將滿36歲，仍持續在國際..."
      },
      {
        "title": "會員大會3度流會 籃協：是否出席屬於個人意志",
        "link": "https://www.cna.com.tw/news/aspt/202601060267.aspx",
        "source": "中央社",
        "published": "2026-01-06T02:00:59+00:00",
        "summary": "中華籃協去年三度召開的會員大會均未達成成會，運動部次長黃啟煌在立法院備詢時表示，對此情況感到不滿，並不排除對相關人員進行懲處。籃協則回應，會員的出席與否屬於個人自由意志，並強調將持續進行審議與溝通，以..."
      },
      {
        "title": "鍾緯澤再回球場不想讓奶奶失望 大專聯賽敲關鍵安",
        "link": "https://www.cna.com.tw/news/aspt/202601060256.aspx",
        "source": "中央社",
        "published": "2026-01-06T01:41:35+00:00",
        "summary": "台北市大野手鍾緯澤於6日在大專棒球聯賽中表現出色，擊出關鍵安打，助隊伍以4比3戰勝中信科大。鍾緯澤曾經面臨低潮，考慮放棄棒球，但因對運動的熱愛以及不想讓從小撫養他的奶奶失望，決定重返球場繼續努力。此次..."
      },
      {
        "title": "大專棒球聯賽莊承翰、邱承奕壓制 北市大複賽3勝",
        "link": "https://www.cna.com.tw/news/aspt/202601060251.aspx",
        "source": "中央社",
        "published": "2026-01-06T01:32:25+00:00",
        "summary": "大專棒球聯賽公開一級複賽中，台北市大於6日對陣中信科大，最終以4比0獲勝，成為複賽首支取得3勝的球隊。比賽中，側投莊承翰表現出色，先發投球8局未失一分，隨後由邱承奕接替後援，成功關門，確保球隊不失分。..."
      },
      {
        "title": "運動推手獎77個單位獲獎 贊助金額破59億創新高",
        "link": "https://www.cna.com.tw/news/aspt/202601060230.aspx",
        "source": "中央社",
        "published": "2026-01-06T01:09:39+00:00",
        "summary": "第17屆運動推手獎將於2024年1月9日在台北表演藝術中心舉行頒獎典禮。今年共有77個單位獲獎，總贊助金額突破新台幣59億元，創下歷年新高。此數據顯示台灣運動產業的蓬勃發展，反映出各界對於運動推廣的重..."
      }
    ]
  },
  "en_news": {
    "Startup": [
      {
        "title": "Why the trans flag emoji is the 5-codepoint sequence it is",
        "link": "https://hecate.pink/blog/2026/trans-flag-emoji",
        "source": "Hacker News",
        "published": "2026-01-06T16:22:06+00:00",
        "summary": "The trans flag emoji, represented by a five-codepoint sequence, has been a topic of discussion regar..."
      },
      {
        "title": "Space Forge plans to manufacture semiconductors from space",
        "link": "https://www.scientificamerican.com/article/the-push-to-make-semiconductors-in-space-just-took-a-serious-leap-forward",
        "source": "Hacker News",
        "published": "2026-01-06T16:06:34+00:00",
        "summary": "Space Forge, a UK-based startup, has announced plans to manufacture semiconductors in space, aiming ..."
      },
      {
        "title": "Vulnerability in Ruby that has existed since 2002",
        "link": "https://nastystereo.com/security/ruby-pack.html",
        "source": "Hacker News",
        "published": "2026-01-06T15:46:24+00:00",
        "summary": "A vulnerability in the Ruby programming language, which has been present since 2002, has come to lig..."
      },
      {
        "title": "Hyundai Introduces Its Next-Gen Atlas Robot at CES 2026 [video]",
        "link": "https://www.youtube.com/watch?v=9e0SQn9uUlw",
        "source": "Hacker News",
        "published": "2026-01-06T15:40:03+00:00",
        "summary": "Hyundai unveiled its next-generation Atlas robot at the Consumer Electronics Show (CES) 2026, showca..."
      },
      {
        "title": "Show HN: GPU Cuckoo Filter – faster queries than Blocked Bloom, with deletion",
        "link": "https://github.com/tdortman/cuckoo-filter",
        "source": "Hacker News",
        "published": "2026-01-06T14:33:21+00:00",
        "summary": "A new project titled \"GPU Cuckoo Filter\" has been introduced on Hacker News, showcasing a data struc..."
      },
      {
        "title": "Are we tired of social media once and for all? On the downfall of social media",
        "link": "https://www.danielbrendel.com/blog/24-are-we-tired-of-social-media-once-and-for-all",
        "source": "Hacker News",
        "published": "2026-01-06T14:15:52+00:00",
        "summary": "The article discusses the declining popularity of social media platforms, highlighting a shift in us..."
      },
      {
        "title": "CES 2026: Taking the Lids Off AMD's Venice and MI400 SoCs",
        "link": "https://chipsandcheese.com/p/ces-2026-taking-the-lids-off-amds",
        "source": "Hacker News",
        "published": "2026-01-06T13:46:04+00:00",
        "summary": "At CES 2026, AMD unveiled its latest System-on-Chip (SoC) offerings, the Venice and MI400, showcasin..."
      },
      {
        "title": "Laylo (YC S20) – Head of Growth (Organic and Partners and Loops and AI) – Remote US",
        "link": "https://www.ycombinator.com/companies/laylo/jobs/ZtLHRXe-head-of-growth",
        "source": "Hacker News",
        "published": "2026-01-06T13:44:37+00:00",
        "summary": "Laylo, a startup that participated in Y Combinator's Summer 2020 batch, is seeking a Head of Growth ..."
      }
    ],
    "Tech News": [
      {
        "title": "Motorola’s first smartwatch promises 13-day battery life and Polar-powered health tracking",
        "link": "https://www.theverge.com/gadgets/851643/moto-watch-android-smarwatch-ces-2026",
        "source": "The Verge",
        "published": "2026-01-06T17:00:00+00:00",
        "summary": "At CES, Motorola announced its first smartwatch, the Moto Watch. According to Motorola, the Android ..."
      },
      {
        "title": "Lenovo’s Auto Twist laptop is going from concept to real product",
        "link": "https://www.theverge.com/news/852251/lenovos-auto-twist-laptop-is-going-from-concept-to-real-product",
        "source": "The Verge",
        "published": "2026-01-06T17:00:00+00:00",
        "summary": "At CES 2026, Lenovo is announcing a new ThinkBook Plus Gen 7 Auto Twist laptop. Once a concept, the ..."
      },
      {
        "title": "The new Lenovo Yoga Pro 9i laptop has a super-bright tandem OLED and magnetic stylus",
        "link": "https://www.theverge.com/news/852276/the-new-lenovo-yoga-pro-9i-laptop-has-a-super-bright-tandem-oled-and-magnetic-stylus",
        "source": "The Verge",
        "published": "2026-01-06T17:00:00+00:00",
        "summary": "Lenovo's new pair of Yoga laptops for CES 2026 are its most powerful and most lightweight models. Th..."
      },
      {
        "title": "Lenovo’s new concept rollable could be the ideal gaming laptop",
        "link": "https://www.theverge.com/tech/852352/lenovo-legion-pro-rollable-gaming-laptop-concept-ces-2026",
        "source": "The Verge",
        "published": "2026-01-06T17:00:00+00:00",
        "summary": "Lenovo is at it again with wild laptop concepts for CES 2026, and the biggest one is the Legion Pro ..."
      },
      {
        "title": "This ThinkPad laptop concept has a rollable display that wraps around its lid",
        "link": "https://www.theverge.com/news/852482/lenovo-thinkpad-rollable-xd-concept-laptop-ces-2026",
        "source": "The Verge",
        "published": "2026-01-06T17:00:00+00:00",
        "summary": "At CES 2026, Lenovo is announcing yet another new concept laptop with a transforming screen: the Thi..."
      },
      {
        "title": "Lenovo’s new All-in-One PC can sync its lighting to your notifications",
        "link": "https://www.theverge.com/news/852860/lenovo-yoga-aio-i-aura-edition-ces-2026",
        "source": "The Verge",
        "published": "2026-01-06T17:00:00+00:00",
        "summary": "If you prefer to have your notifications on silent but don't want to miss anything, Lenovo's new All..."
      },
      {
        "title": "Lenovo’s joining the bandwagon with concept AI glasses",
        "link": "https://www.theverge.com/tech/853434/ces-2026-lenovo-concept-ai-glasses-wearables",
        "source": "The Verge",
        "published": "2026-01-06T17:00:00+00:00",
        "summary": "Lenovo is the latest tech company to get bit by the smart glasses bug. The company just showed off a..."
      },
      {
        "title": "Lenovo’s second SteamOS handheld is the Legion Go 2",
        "link": "https://www.theverge.com/tech/853587/lenovo-legion-go-2-steam-os-annoucement-price-release-date",
        "source": "The Verge",
        "published": "2026-01-06T17:00:00+00:00",
        "summary": "One year ago, Lenovo became the first company besides Valve to announce a handheld with SteamOS inst..."
      }
    ],
    "BBC Top Stories": [
      {
        "title": "The Papers: 'Boots on the ground' and 'one for the road'",
        "link": "https://www.bbc.com/news/articles/cwy17ndew89o?at_medium=RSS&at_campaign=rss",
        "source": "BBC News",
        "published": "2026-01-06T16:55:43+00:00",
        "summary": "British newspapers on Wednesday report on two significant issues: the potential deployment of Britis..."
      },
      {
        "title": "Trump says Venezuela will be 'turning over' up to 50m barrels of oil to US",
        "link": "https://www.bbc.com/news/articles/c4grxzxjjd8o?at_medium=RSS&at_campaign=rss",
        "source": "BBC News",
        "published": "2026-01-06T16:24:38+00:00",
        "summary": "Former President Donald Trump announced that Venezuela could potentially supply the United States wi..."
      },
      {
        "title": "More snow and ice across nearly all of UK as cold snap continues",
        "link": "https://www.bbc.com/news/articles/cly39n1vejpo?at_medium=RSS&at_campaign=rss",
        "source": "BBC News",
        "published": "2026-01-06T16:10:21+00:00",
        "summary": "The Met Office has issued warnings for icy conditions across nearly all of the UK as a cold snap per..."
      },
      {
        "title": "Award-winning actor 'regains feeling in feet' with new MND drug",
        "link": "https://www.bbc.com/news/articles/cpqy9qpyx37o?at_medium=RSS&at_campaign=rss",
        "source": "BBC News",
        "published": "2026-01-06T16:02:39+00:00",
        "summary": "Belfast actor Michael Campbell, known professionally as Michael Patrick, has reportedly regained fee..."
      },
      {
        "title": "Learner drivers face longer wait for tests as lower drink-drive limit proposed",
        "link": "https://www.bbc.com/news/articles/clym5jvgdepo?at_medium=RSS&at_campaign=rss",
        "source": "BBC News",
        "published": "2026-01-06T16:00:28+00:00",
        "summary": "The UK government is considering a proposal to introduce a minimum learning period of up to six mont..."
      },
      {
        "title": "The painful questions for Nato and the EU as Trump threatens Greenland",
        "link": "https://www.bbc.com/news/articles/cpwn2wjzwndo?at_medium=RSS&at_campaign=rss",
        "source": "BBC News",
        "published": "2026-01-06T15:59:30+00:00",
        "summary": "The White House has indicated that the use of the U.S. military remains an option available to the c..."
      }
    ],
    "BBC World": [
      {
        "title": "'It seems unjust to me' - views from Caracas on Maduro's seizure",
        "link": "https://www.bbc.com/news/videos/cn42zz4ypgwo?at_medium=RSS&at_campaign=rss",
        "source": "BBC World",
        "published": "2026-01-06T12:19:09+00:00",
        "summary": "Venezuelans in Caracas have expressed their views regarding the recent U.S. military operation targe..."
      },
      {
        "title": "Six dead and hundreds of flights cancelled as snow causes chaos across Europe",
        "link": "https://www.bbc.com/news/articles/czjg37p34r3o?at_medium=RSS&at_campaign=rss",
        "source": "BBC World",
        "published": "2026-01-06T10:14:02+00:00",
        "summary": "Severe snowstorms across Europe have resulted in the cancellation of hundreds of flights, particular..."
      },
      {
        "title": "US Congressman Doug LaMalfa dies unexpectedly at 65",
        "link": "https://www.bbc.com/news/articles/cgl8y4gx9lyo?at_medium=RSS&at_campaign=rss",
        "source": "BBC World",
        "published": "2026-01-06T09:05:21+00:00",
        "summary": "U.S. Congressman Doug LaMalfa, a Republican from California and ally of former President Donald Trum..."
      },
      {
        "title": "Israel's foreign minister on historic visit to Somaliland",
        "link": "https://www.bbc.com/news/articles/cwyrexdgzn9o?at_medium=RSS&at_campaign=rss",
        "source": "BBC World",
        "published": "2026-01-06T08:23:19+00:00",
        "summary": "Israel's Foreign Minister Eli Cohen visited Somaliland on October 24, 2023, marking a historic momen..."
      },
      {
        "title": "Iran anti-government protests spread to majority of provinces, videos show",
        "link": "https://www.bbc.com/news/articles/cre28d2j2zxo?at_medium=RSS&at_campaign=rss",
        "source": "BBC World",
        "published": "2026-01-06T07:35:23+00:00",
        "summary": "Anti-government protests in Iran have expanded to over 50 towns and cities, including areas traditio..."
      },
      {
        "title": "European allies back Denmark over Trump's threat to annex Greenland",
        "link": "https://www.bbc.com/news/articles/c07xkeee2k3o?at_medium=RSS&at_campaign=rss",
        "source": "BBC World",
        "published": "2026-01-06T06:56:50+00:00",
        "summary": "European allies have expressed support for Denmark following comments from former U.S. President Don..."
      }
    ],
    "BBC Business": [
      {
        "title": "Fujitsu 'not a parasite' for profiting after Horizon scandal, says boss",
        "link": "https://www.bbc.com/news/articles/cdxjnv1qzgxo?at_medium=RSS&at_campaign=rss",
        "source": "BBC Business",
        "published": "2026-01-06T09:56:44+00:00",
        "summary": "Fujitsu's European chief executive defended the company amid criticism for profiting from government..."
      },
      {
        "title": "Drivers over 70 to face eye tests every three years",
        "link": "https://www.bbc.com/news/articles/c205nxy0p31o?at_medium=RSS&at_campaign=rss",
        "source": "BBC Business",
        "published": "2026-01-06T09:03:10+00:00",
        "summary": "Drivers in Britain aged 70 and over will be required to undergo eye tests every three years as part ..."
      },
      {
        "title": "Target 'divisive' Reform in 2026, Keir Starmer tells ministers",
        "link": "https://www.bbc.com/news/articles/c150z39e705o?at_medium=RSS&at_campaign=rss",
        "source": "BBC Business",
        "published": "2026-01-06T08:40:05+00:00",
        "summary": "Labour leader Keir Starmer has outlined the party's strategy to counter the Reform party's influence..."
      },
      {
        "title": "Next raises profit forecast to £1.15bn after bumper Christmas sales",
        "link": "https://www.bbc.com/news/articles/cre27x179zpo?at_medium=RSS&at_campaign=rss",
        "source": "BBC Business",
        "published": "2026-01-06T03:15:07+00:00",
        "summary": "Next, the UK-based retailer, has raised its profit forecast to £1.15 billion following stronger-than..."
      },
      {
        "title": "Electric car discounts are unsustainable, says industry group",
        "link": "https://www.bbc.com/news/articles/c0417v3v21ko?at_medium=RSS&at_campaign=rss",
        "source": "BBC Business",
        "published": "2026-01-06T01:48:31+00:00",
        "summary": "The Society of Motor Manufacturers and Traders (SMMT) has cautioned that current discounts on electr..."
      }
    ],
    "BBC Education": [
      {
        "title": "Fresh snow and ice warnings as Storm Goretti approaches UK",
        "link": "https://www.bbc.com/news/articles/cx2x6z4n2wzo?at_medium=RSS&at_campaign=rss",
        "source": "BBC Education",
        "published": "2026-01-06T11:18:06+00:00",
        "summary": "Storm Goretti is set to impact the UK, bringing fresh snow and ice, which has already resulted in th..."
      }
    ],
    "BBC Health": [
      {
        "title": "New NHS online hospital to focus on eyes, menopause and prostates",
        "link": "https://www.bbc.com/news/articles/c62w3wr92npo?at_medium=RSS&at_campaign=rss",
        "source": "BBC Health",
        "published": "2026-01-06T00:23:32+00:00",
        "summary": "The NHS is set to launch a new online hospital in England in 2024, focusing on three key areas: eye ..."
      },
      {
        "title": "How do cold weather health alerts work?",
        "link": "https://www.bbc.com/news/articles/cd97dkx9g38o?at_medium=RSS&at_campaign=rss",
        "source": "BBC Health",
        "published": "2026-01-06T00:09:06+00:00",
        "summary": "The weather alert service is designed to inform the public about potential health risks associated w..."
      }
    ]
  },
  "ja_news": {
    "頭條": [
      {
        "title": "「サロンパス」の久光製薬、MBOで非上場化へ 4000億円規模",
        "link": "http://www.asahi.com/articles/ASV1651DYV16ULFA00PM.html",
        "source": "朝日新聞",
        "published": "2026-01-06T16:49:38+00:00",
        "summary": "久光製薬は、MBO（経営陣による買収）を通じて非上場化を進めることを発表した。今回の買収額は約4000億円に達する見込みで、これにより同社は上場企業から非上場企業へと移行する。久光製薬は「サロンパス」..."
      },
      {
        "title": "ネイリスト殺害 友人言葉詰まらせ",
        "link": "https://news.yahoo.co.jp/pickup/6565275",
        "source": "Yahoo! Japan",
        "published": "2026-01-06T16:39:17+00:00",
        "summary": "東京都内で発生したネイリストの殺害事件に関連し、友人が報道陣の前で言葉を詰まらせる場面が見られた。友人は被害者との思い出を語り、悲しみを表現した。事件の詳細や容疑者については明らかにされていないが、地..."
      },
      {
        "title": "井上尚弥の判定勝利に父苦言 真意",
        "link": "https://news.yahoo.co.jp/pickup/6565276",
        "source": "Yahoo! Japan",
        "published": "2026-01-06T16:37:21+00:00",
        "summary": "プロボクサーの井上尚弥が判定勝利を収めた試合に対し、父親が苦言を呈した。井上選手は試合後、父の意見を受け止めつつも、自身のパフォーマンスに自信を持っていると述べた。父は、判定結果に対する不満を示し、井..."
      },
      {
        "title": "食品売り場はアメだけ 100均悲鳴",
        "link": "https://news.yahoo.co.jp/pickup/6565273",
        "source": "Yahoo! Japan",
        "published": "2026-01-06T15:59:59+00:00",
        "summary": "100円ショップの食品売り場において、品薄状態が続いている。特に、アメやお菓子などの嗜好品が目立つ一方で、日常的な食品の在庫が不足しているという。これにより、消費者からの不満が高まっており、店舗側は対..."
      },
      {
        "title": "フォードの米新車販売台数 6%増",
        "link": "https://news.yahoo.co.jp/pickup/6565272",
        "source": "Yahoo! Japan",
        "published": "2026-01-06T15:58:50+00:00",
        "summary": "フォードは、2023年の第3四半期における米国での新車販売台数が前年同期比で6%増加したと発表した。これにより、フォードは市場での競争力を強化している。新モデルの投入や電動車両の販売増が寄与したとされ..."
      },
      {
        "title": "停戦後のウクライナに部隊派遣、英仏が署名 英「各地に軍事拠点」",
        "link": "http://www.asahi.com/articles/ASV167V0RV16UHBI007M.html",
        "source": "朝日新聞",
        "published": "2026-01-06T15:47:30+00:00",
        "summary": "イギリスとフランスは、停戦後のウクライナに部隊を派遣するための合意に署名した。イギリスは、ウクライナ各地に軍事拠点を設置する計画を明らかにしており、部隊の派遣はウクライナの防衛力強化を目的としている。..."
      },
      {
        "title": "ランチ代補助でサラダチキンをプラス「実質手取り増」企業にも利点",
        "link": "http://www.asahi.com/articles/ASV124G16V12OXIE041M.html",
        "source": "朝日新聞",
        "published": "2026-01-06T15:30:00+00:00",
        "summary": "企業がランチ代補助を導入し、従業員にサラダチキンを提供する取り組みが注目されている。この施策により、従業員は実質的に手取りが増加する効果が期待されている。企業側にとっても、従業員の健康促進や満足度向上..."
      },
      {
        "title": "米大統領 マドゥロ氏は「暴力的」",
        "link": "https://news.yahoo.co.jp/pickup/6565270",
        "source": "Yahoo! Japan",
        "published": "2026-01-06T15:24:25+00:00",
        "summary": "バイデン米大統領は、ベネズエラのニコラス・マドゥロ大統領を「暴力的」と表現し、同国の人権状況を批判した。バイデン氏は、マドゥロ政権が国民に対して行っている弾圧や暴力行為を非難し、国際社会に対してベネズ..."
      }
    ],
    "國際": [
      {
        "title": "外務省、中国政府の輸出規制強化に抗議 局長「決して許容できず」",
        "link": "https://www.asahi.com/articles/ASV167KGPV16UTFK00ZM.html",
        "source": "朝日新聞",
        "published": "2026-01-06T15:14:59+00:00",
        "summary": "外務省は、中国政府が実施した輸出規制の強化に対し抗議の意を表明した。外務省の局長は、この規制が日本企業に与える影響を懸念し、「決して許容できない」と述べた。抗議の背景には、国際的な貿易の自由を守る必要..."
      },
      {
        "title": "米 グリーンランド巡り選択肢協議",
        "link": "https://news.yahoo.co.jp/pickup/6565264",
        "source": "Yahoo! Japan",
        "published": "2026-01-06T14:36:18+00:00",
        "summary": "アメリカはグリーンランドに関する選択肢について協議を行っている。具体的な内容や日程は明らかにされていないが、グリーンランドの地政学的な重要性が背景にあるとされている。この協議は、アメリカの外交政策や地..."
      },
      {
        "title": "グリーンランドに関する事項「決めるのは住民」 欧州が声明、米牽制",
        "link": "https://www.asahi.com/articles/ASV1652RWV16UHBI02KM.html",
        "source": "朝日新聞",
        "published": "2026-01-06T07:50:18+00:00",
        "summary": "欧州連合（EU）は、グリーンランドに関する問題について「決定権は住民にある」との声明を発表した。この声明は、アメリカ合衆国がグリーンランドに対して影響力を行使しようとする動きに対する牽制を意図している..."
      },
      {
        "title": "国際情勢 米の攻撃がもたらす変化",
        "link": "https://news.yahoo.co.jp/pickup/6565255",
        "source": "Yahoo! Japan",
        "published": "2026-01-06T06:46:20+00:00",
        "summary": "アメリカの攻撃が国際情勢に与える影響についての分析が行われている。特に、攻撃の結果として地域の安全保障や経済状況が変化する可能性が指摘されており、各国の反応や対応が注目されている。これにより、国際関係..."
      },
      {
        "title": "中国、軍民両用品の対日輸出規制強化 レアアース審査厳格化の報道も",
        "link": "https://www.asahi.com/articles/ASV1636TZV16UHBI025M.html",
        "source": "朝日新聞",
        "published": "2026-01-06T06:14:30+00:00",
        "summary": "中国は、軍民両用の製品に対する対日輸出規制を強化する方針を示した。これに伴い、レアアースの輸出に関しても審査を厳格化するとの報道がある。具体的な規制内容や施行日については明らかにされていないが、これに..."
      },
      {
        "title": "グリーンランド巡り米けん制 欧州",
        "link": "https://news.yahoo.co.jp/pickup/6565249",
        "source": "Yahoo! Japan",
        "published": "2026-01-06T06:05:57+00:00",
        "summary": "アメリカがグリーンランドを巡る影響力を強化する中、欧州諸国がこれに対抗する動きを見せている。特にデンマークは、グリーンランドの自治権を尊重しつつ、地域の安定を確保するための外交努力を進めている。アメリ..."
      },
      {
        "title": "韓国大統領 習氏とスマホで自撮り",
        "link": "https://news.yahoo.co.jp/pickup/6565237",
        "source": "Yahoo! Japan",
        "published": "2026-01-06T03:51:07+00:00",
        "summary": "韓国の尹錫悦大統領は、2023年10月に中国の習近平国家主席と会談した際、スマートフォンを使用して自撮りを行った。この自撮りは、両国の関係を強化する意図があるとされ、尹大統領はSNSにその写真を投稿し..."
      },
      {
        "title": "ウクライナ有志連合、6日にパリで首脳会合 安全の保証を最終調整へ",
        "link": "https://www.asahi.com/articles/ASV163J5DV16UHBI01LM.html",
        "source": "朝日新聞",
        "published": "2026-01-06T03:08:11+00:00",
        "summary": "ウクライナ有志連合は、2023年11月6日にパリで首脳会合を開催する。会合では、ウクライナに対する安全保障の保証について最終調整を行う予定であり、参加国の協力を強化することが目的とされている。この会合..."
      }
    ],
    "運動": [
      {
        "title": "岡本和真がWBC言及「戦いたい」",
        "link": "https://news.yahoo.co.jp/pickup/6565274",
        "source": "Yahoo! Japan",
        "published": "2026-01-06T16:15:08+00:00",
        "summary": "プロ野球選手の岡本和真が、2023年のワールド・ベースボール・クラシック（WBC）に出場したい意向を示した。岡本は自身のSNSで「戦いたい」という言葉を用い、代表チームへの参加を希望する気持ちを表明し..."
      },
      {
        "title": "森保J 3月にスコットランド戦",
        "link": "https://news.yahoo.co.jp/pickup/6565271",
        "source": "Yahoo! Japan",
        "published": "2026-01-06T15:43:15+00:00",
        "summary": "日本代表サッカーチーム、通称森保Jは、2024年3月にスコットランド代表と対戦することが決定した。この試合は、2024年のUEFA欧州選手権に向けた準備の一環として行われる。対戦場所や具体的な日程は今..."
      },
      {
        "title": "河村勇輝 ブルズと再び2WAY契約",
        "link": "https://news.yahoo.co.jp/pickup/6565266",
        "source": "Yahoo! Japan",
        "published": "2026-01-06T14:49:12+00:00",
        "summary": "プロバスケットボール選手の河村勇輝が、NBAのシカゴ・ブルズと再び2WAY契約を結んだ。契約の詳細は明らかにされていないが、河村はブルズの選手としてNBAとGリーグでの出場が可能となる。彼は前回の契約..."
      },
      {
        "title": "阪神 甲子園の外国人専用席増席へ",
        "link": "https://news.yahoo.co.jp/pickup/6565261",
        "source": "Yahoo! Japan",
        "published": "2026-01-06T14:14:52+00:00",
        "summary": "阪神タイガースは、甲子園球場における外国人専用席を増設することを決定した。増席は2024年シーズンから実施される予定で、外国人ファンの観戦環境を改善することを目的としている。具体的な増席数や設計の詳細..."
      },
      {
        "title": "岡本和真 入団決め手聞かれ娘エピ",
        "link": "https://news.yahoo.co.jp/pickup/6565257",
        "source": "Yahoo! Japan",
        "published": "2026-01-06T13:23:15+00:00",
        "summary": "プロ野球選手の岡本和真選手が、入団の決め手について語った。彼は、娘からの「お父さんはどのチームに入るの？」という質問が影響を与えたと明かした。岡本選手は、家族の期待を背負い、チームに貢献することを誓っ..."
      },
      {
        "title": "ちゃんと走れる 山川穂高7kg減量",
        "link": "https://news.yahoo.co.jp/pickup/6565253",
        "source": "Yahoo! Japan",
        "published": "2026-01-06T06:17:26+00:00",
        "summary": "プロ野球選手の山川穂高選手が、体重を7kg減量したことを報告した。減量の目的は、より良いパフォーマンスを発揮するためであり、トレーニングや食事管理を徹底した結果だという。山川選手は、減量後も「ちゃんと..."
      },
      {
        "title": "ウルフアロン防衛戦 棚橋社長発表",
        "link": "https://news.yahoo.co.jp/pickup/6565215",
        "source": "Yahoo! Japan",
        "published": "2026-01-06T01:12:37+00:00",
        "summary": "プロレスラーのウルフアロン選手が、次回の防衛戦を行うことが発表された。棚橋弘至社長が記者会見で明らかにしたもので、試合は2023年12月に開催される予定。詳細な対戦相手や会場については今後発表される見..."
      }
    ],
    "商業": [
      {
        "title": "西松屋の創業者 茂理佳弘さん死去",
        "link": "https://news.yahoo.co.jp/pickup/6565277",
        "source": "Yahoo! Japan",
        "published": "2026-01-06T16:51:38+00:00",
        "summary": "西松屋の創業者、茂理佳弘さんが死去した。茂理さんは、1972年に西松屋を創業し、子供服やベビー用品の販売を通じて日本国内で広く知られる存在となった。彼の経営手法やビジョンは、多くの人々に影響を与え、同..."
      },
      {
        "title": "テレビ離れでもBS放送参入「クララが立った！」かみしめたJCOM",
        "link": "https://www.asahi.com/articles/ASTDT34NKTDTULFA01LM.html",
        "source": "朝日新聞",
        "published": "2026-01-06T14:00:00+00:00",
        "summary": "JCOMは、視聴者のテレビ離れが進む中、BS放送に新たに参入した。新たに放送される番組「クララが立った！」は、視聴者に対して新しい体験を提供することを目指している。JCOMは、視聴者のニーズに応えるた..."
      },
      {
        "title": "「クマの胆」フリマ出品 削除要請",
        "link": "https://news.yahoo.co.jp/pickup/6565259",
        "source": "Yahoo! Japan",
        "published": "2026-01-06T13:45:10+00:00",
        "summary": "クマの胆をフリーマーケットで出品した事例に対し、動物愛護団体が削除を要請した。出品された胆は、クマから採取されるもので、国内外での取引が問題視されている。団体は、動物の権利や保護の観点から、こうした行..."
      },
      {
        "title": "フジvs村上世彰、新局面に 関係者「高い球」金脈サンケイビル焦点",
        "link": "https://www.asahi.com/articles/ASV162FH0V16ULFA014M.html",
        "source": "朝日新聞",
        "published": "2026-01-06T13:00:00+00:00",
        "summary": "フジ・メディア・ホールディングスと村上世彰氏の対立が新たな局面を迎えた。関係者によると、焦点はサンケイビルの資産に移っており、双方が「高い球」を投げ合っている状況だ。村上氏は、フジの経営に影響を与える..."
      },
      {
        "title": "主要企業6割が経済政策評価 産経",
        "link": "https://news.yahoo.co.jp/pickup/6565247",
        "source": "Yahoo! Japan",
        "published": "2026-01-06T05:40:13+00:00",
        "summary": "産経新聞の調査によると、主要企業の約60%が政府の経済政策を評価していることが明らかになった。この調査は、企業の経営者や幹部を対象に実施され、経済政策が企業活動に与える影響についての意見が集められた。..."
      },
      {
        "title": "中部電の審査不正 公益通報で発覚",
        "link": "https://news.yahoo.co.jp/pickup/6565234",
        "source": "Yahoo! Japan",
        "published": "2026-01-06T03:36:34+00:00",
        "summary": "中部電力は、審査に関する不正が公益通報により発覚したと発表した。この不正は、審査プロセスにおいて適切な手続きを踏まずに行われたもので、具体的な内容や影響については現在調査中である。会社は再発防止策を講..."
      },
      {
        "title": "さいたまスーパーアリーナ休館へ",
        "link": "https://news.yahoo.co.jp/pickup/6565230",
        "source": "Yahoo! Japan",
        "published": "2026-01-06T02:57:18+00:00",
        "summary": "さいたまスーパーアリーナは、2024年1月から休館することが発表された。休館の理由は、施設の改修工事を行うためで、工事期間は約1年を予定している。改修後は、より多機能な施設として再開される見込みで、地..."
      },
      {
        "title": "経済団体新年会 中国大使欠席へ",
        "link": "https://news.yahoo.co.jp/pickup/6565228",
        "source": "Yahoo! Japan",
        "published": "2026-01-06T02:31:45+00:00",
        "summary": "経済団体の新年会が開催される中、中国大使が欠席することが明らかになった。新年会は日本の経済界の重要なイベントであり、通常は多くの外国大使が出席するが、今回は中国大使の不参加が注目されている。欠席の理由..."
      }
    ],
    "文化": [
      {
        "title": "88歳死亡 顔殴った疑いで息子逮捕",
        "link": "https://news.yahoo.co.jp/pickup/6565260",
        "source": "Yahoo! Japan",
        "published": "2026-01-06T13:59:20+00:00",
        "summary": "88歳の女性が死亡し、息子が顔を殴った疑いで逮捕された。事件は2023年10月に発生し、息子は警察の調べに対し、暴力を振るったことを認めている。女性は自宅で発見され、死因は現在調査中である。警察は詳細..."
      },
      {
        "title": "巨大落石に液状化 5強の鳥取島根",
        "link": "https://news.yahoo.co.jp/pickup/6565252",
        "source": "Yahoo! Japan",
        "published": "2026-01-06T06:07:43+00:00",
        "summary": "2023年10月、鳥取県と島根県で発生した震度5強の地震により、巨大な落石や液状化現象が確認された。地震の影響で、特に山間部では落石が多発し、道路が通行止めとなるなどの被害が報告されている。また、液状..."
      },
      {
        "title": "暴行動画の学校 大会辞退の部活も",
        "link": "https://news.yahoo.co.jp/pickup/6565250",
        "source": "Yahoo! Japan",
        "published": "2026-01-06T05:59:09+00:00",
        "summary": "暴行動画が問題となった学校では、関与した部活動が全国大会への辞退を決定した。この学校は、動画が公開されたことを受けて、事態を重く受け止めている。学校側は、暴力行為の再発防止に向けた取り組みを進める意向..."
      },
      {
        "title": "地検でカセットボンベ爆発か 山口",
        "link": "https://news.yahoo.co.jp/pickup/6565246",
        "source": "Yahoo! Japan",
        "published": "2026-01-06T05:27:45+00:00",
        "summary": "山口県の地検で、カセットボンベが爆発したとの情報が入った。爆発は、2023年10月に発生し、現場では消防や警察が出動し、周辺の安全確保に努めている。負傷者の有無や爆発の原因については、現在調査が進めら..."
      },
      {
        "title": "山陰で繰り返し余震 おびえた住民",
        "link": "https://news.yahoo.co.jp/pickup/6565241",
        "source": "Yahoo! Japan",
        "published": "2026-01-06T04:28:53+00:00",
        "summary": "山陰地方で、最近繰り返し余震が発生しており、住民が不安を抱えている。余震は特に強い揺れを伴うことがあり、住民は避難所に避難するなどの対策を講じている。地元自治体は、住民に対して安全確保のための情報提供..."
      }
    ],
    "娛樂": [
      {
        "title": "映画監督 タル・ベーラさん死去",
        "link": "https://news.yahoo.co.jp/pickup/6565258",
        "source": "Yahoo! Japan",
        "published": "2026-01-06T13:28:35+00:00",
        "summary": "映画監督のタル・ベーラさんが死去した。享年82歳で、彼はハンガリー出身の著名な映画作家であり、独特の映像美と深いテーマ性で知られていた。ベーラさんは数々の国際映画祭で受賞歴があり、特に『サタンタンゴ』..."
      },
      {
        "title": "生田斗真 ソロ歌手としてデビュー",
        "link": "https://news.yahoo.co.jp/pickup/6565256",
        "source": "Yahoo! Japan",
        "published": "2026-01-06T13:09:16+00:00",
        "summary": "俳優の生田斗真が、ソロ歌手としてデビューすることを発表した。デビューシングルは2024年1月にリリース予定で、彼自身が作詞を手掛けた楽曲が収録される。生田は、音楽活動に対する思いを語り、ファンへの感謝..."
      },
      {
        "title": "松井珠理奈 7日に辻本と結婚会見",
        "link": "https://news.yahoo.co.jp/pickup/6565254",
        "source": "Yahoo! Japan",
        "published": "2026-01-06T07:00:27+00:00",
        "summary": "元AKB48の松井珠理奈さんが、辻本さんとの結婚会見を2023年11月7日に行うことを発表した。会見の詳細や場所については明らかにされていないが、二人の新たな門出を祝う場となる見込みである。松井さんは..."
      },
      {
        "title": "中島裕翔が体調不良 イベント中止",
        "link": "https://news.yahoo.co.jp/pickup/6565233",
        "source": "Yahoo! Japan",
        "published": "2026-01-06T03:25:12+00:00",
        "summary": "俳優の中島裕翔が体調不良のため、予定されていたイベントを中止することが発表された。具体的な体調の詳細や中止の日時については明らかにされていない。ファンや関係者には影響を与える事態となり、今後の活動につ..."
      },
      {
        "title": "TBS日比麻音子アナ 結婚を報告",
        "link": "https://news.yahoo.co.jp/pickup/6565232",
        "source": "Yahoo! Japan",
        "published": "2026-01-06T03:12:57+00:00",
        "summary": "TBSのアナウンサー、日比麻音子さんが自身の結婚を報告した。具体的な結婚相手や日付についての詳細は明らかにされていないが、日比アナは自身のSNSを通じてこの喜びを伝えた。彼女は視聴者に感謝の意を示し、..."
      },
      {
        "title": "やついいちろう51歳 第1子誕生",
        "link": "https://news.yahoo.co.jp/pickup/6565227",
        "source": "Yahoo! Japan",
        "published": "2026-01-06T02:39:44+00:00",
        "summary": "お笑いタレントのやついいちろうさん（51歳）が、第一子となる女児を出産したことを発表した。出産は2023年10月に行われ、母子ともに健康であるという。やついさんは自身のSNSを通じて喜びを報告し、家族..."
      },
      {
        "title": "SnowMan 地震で交通乱れ開演変更",
        "link": "https://news.yahoo.co.jp/pickup/6565205",
        "source": "Yahoo! Japan",
        "published": "2026-01-06T00:34:16+00:00",
        "summary": "人気グループSnowManは、地震の影響により交通が乱れたため、予定していた公演の開演時間を変更した。具体的な変更内容や影響を受けた公演の詳細は明らかにされていないが、ファンに対しては公式サイトを通じ..."
      }
    ]
  }
}